Metadata-Version: 2.1
Name: micropython-ndeflib
Version: 0.0.2
Summary: NDEF library for MicroPython based on NDEF library
Home-page: https://github.com/agama-point/micropython-ndeflib
Author: Petr Kracik
Author-email: petrkr@petrkr.net
License: UNKNOWN
Platform: UNKNOWN
Classifier: Programming Language :: Python :: 3
Classifier: License :: OSI Approved :: ISC License (ISCL)
Classifier: Operating System :: OS Independent
Classifier: Development Status :: 4 - Beta
Requires-Python: >=3.4
